StreamProcessingWithApacheFlinkZhongwenban/README.md
StreamProcessingWithApacheFlinkZhongwenban/__init__.py
StreamProcessingWithApacheFlinkZhongwenban/__main__.py
StreamProcessingWithApacheFlinkZhongwenban/file.epub
StreamProcessingWithApacheFlinkZhongwenban/index.html
StreamProcessingWithApacheFlinkZhongwenban/css/__init__.py
StreamProcessingWithApacheFlinkZhongwenban/css/annotations.css
StreamProcessingWithApacheFlinkZhongwenban/css/main.css
StreamProcessingWithApacheFlinkZhongwenban/css/normalize.css
StreamProcessingWithApacheFlinkZhongwenban/css/popup.css
StreamProcessingWithApacheFlinkZhongwenban/font/__init__.py
StreamProcessingWithApacheFlinkZhongwenban/font/fontello.eot
StreamProcessingWithApacheFlinkZhongwenban/font/fontello.svg
StreamProcessingWithApacheFlinkZhongwenban/font/fontello.ttf
StreamProcessingWithApacheFlinkZhongwenban/font/fontello.woff
StreamProcessingWithApacheFlinkZhongwenban/img/__init__.py
StreamProcessingWithApacheFlinkZhongwenban/img/annotator-glyph-sprite.png
StreamProcessingWithApacheFlinkZhongwenban/img/annotator-icon-sprite.png
StreamProcessingWithApacheFlinkZhongwenban/img/apple-touch-icon.png
StreamProcessingWithApacheFlinkZhongwenban/img/cancelfullscreen.png
StreamProcessingWithApacheFlinkZhongwenban/img/close.png
StreamProcessingWithApacheFlinkZhongwenban/img/fullscreen.png
StreamProcessingWithApacheFlinkZhongwenban/img/loader.gif
StreamProcessingWithApacheFlinkZhongwenban/img/menu-icon.png
StreamProcessingWithApacheFlinkZhongwenban/img/save.png
StreamProcessingWithApacheFlinkZhongwenban/img/saved.png
StreamProcessingWithApacheFlinkZhongwenban/img/settings-s.png
StreamProcessingWithApacheFlinkZhongwenban/img/settings.png
StreamProcessingWithApacheFlinkZhongwenban/img/star.png
StreamProcessingWithApacheFlinkZhongwenban/js/__init__.py
StreamProcessingWithApacheFlinkZhongwenban/js/epub.js
StreamProcessingWithApacheFlinkZhongwenban/js/epub.min.js
StreamProcessingWithApacheFlinkZhongwenban/js/epub.min.map
stream_processing_with_apache_flink_zhongwenban-2024.3.6.0.dist-info/METADATA
stream_processing_with_apache_flink_zhongwenban-2024.3.6.0.dist-info/WHEEL
stream_processing_with_apache_flink_zhongwenban-2024.3.6.0.dist-info/entry_points.txt
stream_processing_with_apache_flink_zhongwenban-2024.3.6.0.dist-info/top_level.txt
stream_processing_with_apache_flink_zhongwenban-2024.3.6.0.dist-info/RECORD
